{
  "id": "c6117316-dc6c-4016-98ef-430fbc75b8ce",
  "prevId": "00000000-0000-0000-0000-000000000000",
  "version": "7",
  "dialect": "postgresql",
  "tables": {
    "public.data_uploads": {
      "name": "data_uploads",
      "schema": "",
      "columns": {
        "id": {
          "name": "id",
          "type": "uuid",
          "primaryKey": true,
          "notNull": true,
          "default": "gen_random_uuid()"
        },
        "source": {
          "name": "source",
          "type": "upload_source",
          "typeSchema": "public",
          "primaryKey": false,
          "notNull": true,
          "default": "'admin'"
        },
        "status": {
          "name": "status",
          "type": "upload_status",
          "typeSchema": "public",
          "primaryKey": false,
          "notNull": true,
          "default": "'pending'"
        },
        "filename": {
          "name": "filename",
          "type": "text",
          "primaryKey": false,
          "notNull": true
        },
        "original_filename": {
          "name": "original_filename",
          "type": "text",
          "primaryKey": false,
          "notNull": false
        },
        "storage_path": {
          "name": "storage_path",
          "type": "text",
          "primaryKey": false,
          "notNull": false
        },
        "category": {
          "name": "category",
          "type": "text",
          "primaryKey": false,
          "notNull": false
        },
        "indicator_slug": {
          "name": "indicator_slug",
          "type": "text",
          "primaryKey": false,
          "notNull": false
        },
        "geography_code": {
          "name": "geography_code",
          "type": "text",
          "primaryKey": false,
          "notNull": false
        },
        "uploaded_by": {
          "name": "uploaded_by",
          "type": "text",
          "primaryKey": false,
          "notNull": true
        },
        "row_count": {
          "name": "row_count",
          "type": "integer",
          "primaryKey": false,
          "notNull": true,
          "default": 0
        },
        "error_message": {
          "name": "error_message",
          "type": "text",
          "primaryKey": false,
          "notNull": false
        },
        "created_at": {
          "name": "created_at",
          "type": "timestamp with time zone",
          "primaryKey": false,
          "notNull": true,
          "default": "now()"
        },
        "completed_at": {
          "name": "completed_at",
          "type": "timestamp with time zone",
          "primaryKey": false,
          "notNull": false
        }
      },
      "indexes": {
        "data_uploads_created_at_idx": {
          "name": "data_uploads_created_at_idx",
          "columns": [
            {
              "expression": "created_at",
              "isExpression": false,
              "asc": true,
              "nulls": "last"
            }
          ],
          "isUnique": false,
          "concurrently": false,
          "method": "btree",
          "with": {}
        },
        "data_uploads_indicator_idx": {
          "name": "data_uploads_indicator_idx",
          "columns": [
            {
              "expression": "indicator_slug",
              "isExpression": false,
              "asc": true,
              "nulls": "last"
            }
          ],
          "isUnique": false,
          "concurrently": false,
          "method": "btree",
          "with": {}
        }
      },
      "foreignKeys": {
        "data_uploads_indicator_slug_indicators_slug_fk": {
          "name": "data_uploads_indicator_slug_indicators_slug_fk",
          "tableFrom": "data_uploads",
          "tableTo": "indicators",
          "columnsFrom": [
            "indicator_slug"
          ],
          "columnsTo": [
            "slug"
          ],
          "onDelete": "no action",
          "onUpdate": "no action"
        },
        "data_uploads_geography_code_geographies_code_fk": {
          "name": "data_uploads_geography_code_geographies_code_fk",
          "tableFrom": "data_uploads",
          "tableTo": "geographies",
          "columnsFrom": [
            "geography_code"
          ],
          "columnsTo": [
            "code"
          ],
          "onDelete": "no action",
          "onUpdate": "no action"
        }
      },
      "compositePrimaryKeys": {},
      "uniqueConstraints": {},
      "policies": {},
      "checkConstraints": {},
      "isRLSEnabled": false
    },
    "public.geographies": {
      "name": "geographies",
      "schema": "",
      "columns": {
        "code": {
          "name": "code",
          "type": "text",
          "primaryKey": true,
          "notNull": true
        },
        "name_en": {
          "name": "name_en",
          "type": "text",
          "primaryKey": false,
          "notNull": true
        },
        "name_fr": {
          "name": "name_fr",
          "type": "text",
          "primaryKey": false,
          "notNull": false
        },
        "type": {
          "name": "type",
          "type": "text",
          "primaryKey": false,
          "notNull": true
        },
        "parent_code": {
          "name": "parent_code",
          "type": "text",
          "primaryKey": false,
          "notNull": false
        },
        "population": {
          "name": "population",
          "type": "integer",
          "primaryKey": false,
          "notNull": false
        },
        "latitude": {
          "name": "latitude",
          "type": "numeric",
          "primaryKey": false,
          "notNull": false
        },
        "longitude": {
          "name": "longitude",
          "type": "numeric",
          "primaryKey": false,
          "notNull": false
        },
        "created_at": {
          "name": "created_at",
          "type": "timestamp with time zone",
          "primaryKey": false,
          "notNull": true,
          "default": "now()"
        },
        "updated_at": {
          "name": "updated_at",
          "type": "timestamp with time zone",
          "primaryKey": false,
          "notNull": true,
          "default": "now()"
        }
      },
      "indexes": {},
      "foreignKeys": {},
      "compositePrimaryKeys": {},
      "uniqueConstraints": {},
      "policies": {},
      "checkConstraints": {},
      "isRLSEnabled": false
    },
    "public.indicator_values": {
      "name": "indicator_values",
      "schema": "",
      "columns": {
        "id": {
          "name": "id",
          "type": "uuid",
          "primaryKey": true,
          "notNull": true,
          "default": "gen_random_uuid()"
        },
        "indicator_slug": {
          "name": "indicator_slug",
          "type": "text",
          "primaryKey": false,
          "notNull": true
        },
        "geography_code": {
          "name": "geography_code",
          "type": "text",
          "primaryKey": false,
          "notNull": true
        },
        "year": {
          "name": "year",
          "type": "integer",
          "primaryKey": false,
          "notNull": true
        },
        "quarter": {
          "name": "quarter",
          "type": "integer",
          "primaryKey": false,
          "notNull": false
        },
        "month": {
          "name": "month",
          "type": "integer",
          "primaryKey": false,
          "notNull": false
        },
        "label": {
          "name": "label",
          "type": "text",
          "primaryKey": false,
          "notNull": false
        },
        "value": {
          "name": "value",
          "type": "numeric",
          "primaryKey": false,
          "notNull": true
        },
        "confidence_low": {
          "name": "confidence_low",
          "type": "numeric",
          "primaryKey": false,
          "notNull": false
        },
        "confidence_high": {
          "name": "confidence_high",
          "type": "numeric",
          "primaryKey": false,
          "notNull": false
        },
        "is_forecast": {
          "name": "is_forecast",
          "type": "boolean",
          "primaryKey": false,
          "notNull": true,
          "default": false
        },
        "model_id": {
          "name": "model_id",
          "type": "text",
          "primaryKey": false,
          "notNull": false
        },
        "upload_id": {
          "name": "upload_id",
          "type": "uuid",
          "primaryKey": false,
          "notNull": false
        },
        "ingested_at": {
          "name": "ingested_at",
          "type": "timestamp with time zone",
          "primaryKey": false,
          "notNull": true,
          "default": "now()"
        },
        "ingested_by": {
          "name": "ingested_by",
          "type": "text",
          "primaryKey": false,
          "notNull": true
        },
        "is_current": {
          "name": "is_current",
          "type": "boolean",
          "primaryKey": false,
          "notNull": true,
          "default": true
        }
      },
      "indexes": {
        "indicator_values_lookup_idx": {
          "name": "indicator_values_lookup_idx",
          "columns": [
            {
              "expression": "indicator_slug",
              "isExpression": false,
              "asc": true,
              "nulls": "last"
            },
            {
              "expression": "geography_code",
              "isExpression": false,
              "asc": true,
              "nulls": "last"
            },
            {
              "expression": "year",
              "isExpression": false,
              "asc": true,
              "nulls": "last"
            },
            {
              "expression": "is_current",
              "isExpression": false,
              "asc": true,
              "nulls": "last"
            }
          ],
          "isUnique": false,
          "concurrently": false,
          "method": "btree",
          "with": {}
        },
        "indicator_values_upload_idx": {
          "name": "indicator_values_upload_idx",
          "columns": [
            {
              "expression": "upload_id",
              "isExpression": false,
              "asc": true,
              "nulls": "last"
            }
          ],
          "isUnique": false,
          "concurrently": false,
          "method": "btree",
          "with": {}
        }
      },
      "foreignKeys": {
        "indicator_values_indicator_slug_indicators_slug_fk": {
          "name": "indicator_values_indicator_slug_indicators_slug_fk",
          "tableFrom": "indicator_values",
          "tableTo": "indicators",
          "columnsFrom": [
            "indicator_slug"
          ],
          "columnsTo": [
            "slug"
          ],
          "onDelete": "no action",
          "onUpdate": "no action"
        },
        "indicator_values_geography_code_geographies_code_fk": {
          "name": "indicator_values_geography_code_geographies_code_fk",
          "tableFrom": "indicator_values",
          "tableTo": "geographies",
          "columnsFrom": [
            "geography_code"
          ],
          "columnsTo": [
            "code"
          ],
          "onDelete": "no action",
          "onUpdate": "no action"
        },
        "indicator_values_upload_id_data_uploads_id_fk": {
          "name": "indicator_values_upload_id_data_uploads_id_fk",
          "tableFrom": "indicator_values",
          "tableTo": "data_uploads",
          "columnsFrom": [
            "upload_id"
          ],
          "columnsTo": [
            "id"
          ],
          "onDelete": "no action",
          "onUpdate": "no action"
        }
      },
      "compositePrimaryKeys": {},
      "uniqueConstraints": {},
      "policies": {},
      "checkConstraints": {},
      "isRLSEnabled": false
    },
    "public.indicators": {
      "name": "indicators",
      "schema": "",
      "columns": {
        "slug": {
          "name": "slug",
          "type": "text",
          "primaryKey": true,
          "notNull": true
        },
        "name_en": {
          "name": "name_en",
          "type": "text",
          "primaryKey": false,
          "notNull": true
        },
        "name_fr": {
          "name": "name_fr",
          "type": "text",
          "primaryKey": false,
          "notNull": false
        },
        "category": {
          "name": "category",
          "type": "text",
          "primaryKey": false,
          "notNull": true
        },
        "description_en": {
          "name": "description_en",
          "type": "text",
          "primaryKey": false,
          "notNull": true
        },
        "description_fr": {
          "name": "description_fr",
          "type": "text",
          "primaryKey": false,
          "notNull": false
        },
        "unit": {
          "name": "unit",
          "type": "text",
          "primaryKey": false,
          "notNull": true
        },
        "higher_is_better": {
          "name": "higher_is_better",
          "type": "boolean",
          "primaryKey": false,
          "notNull": false
        },
        "source_en": {
          "name": "source_en",
          "type": "text",
          "primaryKey": false,
          "notNull": true
        },
        "source_fr": {
          "name": "source_fr",
          "type": "text",
          "primaryKey": false,
          "notNull": false
        },
        "source_url": {
          "name": "source_url",
          "type": "text",
          "primaryKey": false,
          "notNull": true,
          "default": "''"
        },
        "methodology_en": {
          "name": "methodology_en",
          "type": "text",
          "primaryKey": false,
          "notNull": true
        },
        "methodology_fr": {
          "name": "methodology_fr",
          "type": "text",
          "primaryKey": false,
          "notNull": false
        },
        "license": {
          "name": "license",
          "type": "text",
          "primaryKey": false,
          "notNull": true
        },
        "update_frequency": {
          "name": "update_frequency",
          "type": "text",
          "primaryKey": false,
          "notNull": true
        },
        "last_updated": {
          "name": "last_updated",
          "type": "text",
          "primaryKey": false,
          "notNull": true
        },
        "featured": {
          "name": "featured",
          "type": "boolean",
          "primaryKey": false,
          "notNull": true,
          "default": false
        },
        "is_sample": {
          "name": "is_sample",
          "type": "boolean",
          "primaryKey": false,
          "notNull": true,
          "default": true
        },
        "shape": {
          "name": "shape",
          "type": "text",
          "primaryKey": false,
          "notNull": true,
          "default": "'timeseries'"
        },
        "composition_categories": {
          "name": "composition_categories",
          "type": "jsonb",
          "primaryKey": false,
          "notNull": false,
          "default": "'null'::jsonb"
        },
        "created_at": {
          "name": "created_at",
          "type": "timestamp with time zone",
          "primaryKey": false,
          "notNull": true,
          "default": "now()"
        },
        "updated_at": {
          "name": "updated_at",
          "type": "timestamp with time zone",
          "primaryKey": false,
          "notNull": true,
          "default": "now()"
        }
      },
      "indexes": {},
      "foreignKeys": {},
      "compositePrimaryKeys": {},
      "uniqueConstraints": {},
      "policies": {},
      "checkConstraints": {},
      "isRLSEnabled": false
    }
  },
  "enums": {
    "public.upload_source": {
      "name": "upload_source",
      "schema": "public",
      "values": [
        "admin",
        "etl",
        "seed"
      ]
    },
    "public.upload_status": {
      "name": "upload_status",
      "schema": "public",
      "values": [
        "pending",
        "success",
        "failed"
      ]
    }
  },
  "schemas": {},
  "sequences": {},
  "roles": {},
  "policies": {},
  "views": {},
  "_meta": {
    "columns": {},
    "schemas": {},
    "tables": {}
  }
}